pinellm/__init__.py
pinellm/errors.py
pinellm/config/__init__.py
pinellm/config/config_manager.py
pinellm/config/supplier.py
pinellm/config/built/__init__.py
pinellm/config/built/emb_models.py
pinellm/config/built/models.py
pinellm/config/built/suppliers.py
pinellm/config/built/tools.py
pinellm/llm_chat/__init__.py
pinellm/llm_chat/cost.py
pinellm/llm_chat/error_code.py
pinellm/llm_chat/request.py
pinellm/llm_emb/__init__.py
pinellm/llm_emb/cost.py
pinellm/llm_emb/requiest.py
pinellm/schemas/__init__.py
pinellm/schemas/chat_request.py
pinellm/schemas/emb_request.py
pinellm/schemas/safedot.py
pinellm/tools/__init__.py
pinellm/tools/tools_info.py
pinellm/tools/tools_utilize.py
pinellm/tools/basic/__init__.py
pinellm/tools/basic/base_image.py
pinellm/tools/basic/command.py
pinellm/tools/basic/get_basic_info.py
pinellm/tools/basic/get_weather.py
pinellm-1.0.4.dist-info/LICENSE
pinellm-1.0.4.dist-info/METADATA
pinellm-1.0.4.dist-info/WHEEL
pinellm-1.0.4.dist-info/top_level.txt
pinellm-1.0.4.dist-info/RECORD
