Metadata-Version: 2.1
Name: pinellm
Version: 1.0.4
Summary: A Python library for managing LLM chat models
Home-page: https://github.com/PineKings/pinellm
Author: PineKing
Author-email: work.wss@icloud.com
Classifier: Programming Language :: Python :: 3
Classifier: License :: OSI Approved :: MIT License
Classifier: Operating System :: OS Independent
Requires-Python: >=3.12
License-File: LICENSE
Requires-Dist: requests
Requires-Dist: python-dotenv
